<?xml version='1.0' encoding='UTF-8'?>

<gameList>

<game>
	<name>Audio - Switch to HDMI Output</name>
	<path>/mnt/store/Emulation/Games/System/Audio - Switch to HDMI Output.sh</path>
	<desc></desc>
	<publisher></publisher>
	<developer></developer>
	<releasedate></releasedate>
	<image></image>
	<genre></genre>
	<rating>0.0</rating>
	<players></players>
</game>

<game>
	<name>Audio - Switch to Headphone Out</name>
	<path>/mnt/store/Emulation/Games/System/Audio - Switch to Headphone Out.sh</path>
	<desc></desc>
	<publisher></publisher>
	<developer></developer>
	<releasedate></releasedate>
	<image></image>
	<genre></genre>
	<rating>0.0</rating>
	<players></players>
</game>

<game>
	<name>Audio - Switch to Mocreo Speaker</name>
	<path>/mnt/store/Emulation/Games/System/Audio - Switch to Mocreo Speaker.sh</path>
	<desc></desc>
	<publisher></publisher>
	<developer></developer>
	<releasedate></releasedate>
	<image></image>
	<genre></genre>
	<rating>0.0</rating>
	<players></players>
</game>

<game>
	<name>Audio - Switch to Philips Headphones</name>
	<path>/mnt/store/Emulation/Games/System/Audio - Switch to Philips Headphones.sh</path>
	<desc></desc>
	<publisher></publisher>
	<developer></developer>
	<releasedate></releasedate>
	<image></image>
	<genre></genre>
	<rating>0.0</rating>
	<players></players>
</game>

<game>
	<name>Audio - Switch to Q Acoustics Speaker</name>
	<path>/mnt/store/Emulation/Games/System/Audio - Switch to Q Acoustics Speaker.sh</path>
	<desc></desc>
	<publisher></publisher>
	<developer></developer>
	<releasedate></releasedate>
	<image></image>
	<genre></genre>
	<rating>0.0</rating>
	<players></players>
</game>

<game>
	<name>Lights - Off</name>
	<path>/mnt/store/Emulation/Games/System/Lights - Off.sh</path>
	<desc></desc>
	<publisher></publisher>
	<developer></developer>
	<releasedate></releasedate>
	<image></image>
	<genre></genre>
	<rating>0.0</rating>
	<players></players>
</game>

<game>
	<name>Power - Off</name>
	<path>/mnt/store/Emulation/Games/System/Power - Off.sh</path>
	<desc></desc>
	<publisher></publisher>
	<developer></developer>
	<releasedate></releasedate>
	<image></image>
	<genre></genre>
	<rating>0.0</rating>
	<players></players>
</game>

<game>
	<name>Power - Reboot</name>
	<path>/mnt/store/Emulation/Games/System/Power - Reboot.sh</path>
	<desc></desc>
	<publisher></publisher>
	<developer></developer>
	<releasedate></releasedate>
	<image></image>
	<genre></genre>
	<rating>0.0</rating>
	<players></players>
</game>

<game>
	<name>Power - Restart XOrg</name>
	<path>/mnt/store/Emulation/Games/System/Power - Restart XOrg.sh</path>
	<desc></desc>
	<publisher></publisher>
	<developer></developer>
	<releasedate></releasedate>
	<image></image>
	<genre></genre>
	<rating>0.0</rating>
	<players></players>
</game>

</gameList>
